{
  "AWSTemplateFormatVersion": "2010-09-09",
  "Description": "The AWS CloudFormation template for this Serverless application",
  "Resources": {
    "ServerlessDeploymentBucket": {
      "Type": "AWS::S3::Bucket",
      "Properties": {
        "BucketEncryption": {
          "ServerSideEncryptionConfiguration": [
            {
              "ServerSideEncryptionByDefault": {
                "SSEAlgorithm": "AES256"
              }
            }
          ]
        }
      }
    },
    "AppLogGroup": {
      "Type": "AWS::Logs::LogGroup",
      "Properties": {
        "LogGroupName": "/aws/lambda/strava-segments-api-production-app"
      }
    },
    "IamRoleLambdaExecution": {
      "Type": "AWS::IAM::Role",
      "Properties": {
        "AssumeRolePolicyDocument": {
          "Version": "2012-10-17",
          "Statement": [
            {
              "Effect": "Allow",
              "Principal": {
                "Service": [
                  "lambda.amazonaws.com"
                ]
              },
              "Action": [
                "sts:AssumeRole"
              ]
            }
          ]
        },
        "Policies": [
          {
            "PolicyName": {
              "Fn::Join": [
                "-",
                [
                  "production",
                  "strava-segments-api",
                  "lambda"
                ]
              ]
            },
            "PolicyDocument": {
              "Version": "2012-10-17",
              "Statement": [
                {
                  "Effect": "Allow",
                  "Action": [
                    "logs:CreateLogStream"
                  ],
                  "Resource": [
                    {
                      "Fn::Sub": "arn:${AWS::Partition}:logs:${AWS::Region}:${AWS::AccountId}:log-group:/aws/lambda/strava-segments-api-production*:*"
                    }
                  ]
                },
                {
                  "Effect": "Allow",
                  "Action": [
                    "logs:PutLogEvents"
                  ],
                  "Resource": [
                    {
                      "Fn::Sub": "arn:${AWS::Partition}:logs:${AWS::Region}:${AWS::AccountId}:log-group:/aws/lambda/strava-segments-api-production*:*:*"
                    }
                  ]
                }
              ]
            }
          }
        ],
        "Path": "/",
        "RoleName": {
          "Fn::Join": [
            "-",
            [
              "strava-segments-api",
              "production",
              {
                "Ref": "AWS::Region"
              },
              "lambdaRole"
            ]
          ]
        }
      }
    },
    "AppLambdaFunction": {
      "Type": "AWS::Lambda::Function",
      "Properties": {
        "Code": {
          "S3Bucket": {
            "Ref": "ServerlessDeploymentBucket"
          },
          "S3Key": "serverless/strava-segments-api/production/1568587342114-2019-09-15T22:42:22.114Z/strava-segments-api.zip"
        },
        "FunctionName": "strava-segments-api-production-app",
        "Handler": "src/handlers/stravaSegments.getToken",
        "MemorySize": 1024,
        "Role": {
          "Fn::GetAtt": [
            "IamRoleLambdaExecution",
            "Arn"
          ]
        },
        "Runtime": "nodejs10.x",
        "Timeout": 6,
        "Environment": {
          "Variables": {
            "NODE_ENV": "production"
          }
        }
      },
      "DependsOn": [
        "AppLogGroup",
        "IamRoleLambdaExecution"
      ]
    },
    "AppLambdaVersion5re8i6ATiCM2Lv4joawdMQJI3Mvco3R6H5cLC3ZLT2I": {
      "Type": "AWS::Lambda::Version",
      "DeletionPolicy": "Retain",
      "Properties": {
        "FunctionName": {
          "Ref": "AppLambdaFunction"
        },
        "CodeSha256": "Fu+AF2c1aK/wJlRyYBxCwE1aExPGvhtlriWtEFb+MbQ="
      }
    },
    "ApiGatewayRestApi": {
      "Type": "AWS::ApiGateway::RestApi",
      "Properties": {
        "Name": "production-strava-segments-api",
        "EndpointConfiguration": {
          "Types": [
            "EDGE"
          ]
        }
      }
    },
    "ApiGatewayResourceFoo": {
      "Type": "AWS::ApiGateway::Resource",
      "Properties": {
        "ParentId": {
          "Fn::GetAtt": [
            "ApiGatewayRestApi",
            "RootResourceId"
          ]
        },
        "PathPart": "foo",
        "RestApiId": {
          "Ref": "ApiGatewayRestApi"
        }
      }
    },
    "ApiGatewayResourceProxyVar": {
      "Type": "AWS::ApiGateway::Resource",
      "Properties": {
        "ParentId": {
          "Fn::GetAtt": [
            "ApiGatewayRestApi",
            "RootResourceId"
          ]
        },
        "PathPart": "{proxy+}",
        "RestApiId": {
          "Ref": "ApiGatewayRestApi"
        }
      }
    },
    "ApiGatewayMethodFooOptions": {
      "Type": "AWS::ApiGateway::Method",
      "Properties": {
        "AuthorizationType": "NONE",
        "HttpMethod": "OPTIONS",
        "MethodResponses": [
          {
            "StatusCode": "200",
            "ResponseParameters": {
              "method.response.header.Access-Control-Allow-Origin": true,
              "method.response.header.Access-Control-Allow-Headers": true,
              "method.response.header.Access-Control-Allow-Methods": true,
              "method.response.header.Access-Control-Allow-Credentials": true
            },
            "ResponseModels": {}
          }
        ],
        "RequestParameters": {},
        "Integration": {
          "Type": "MOCK",
          "RequestTemplates": {
            "application/json": "{statusCode:200}"
          },
          "ContentHandling": "CONVERT_TO_TEXT",
          "IntegrationResponses": [
            {
              "StatusCode": "200",
              "ResponseParameters": {
                "method.response.header.Access-Control-Allow-Origin": "'*'",
                "method.response.header.Access-Control-Allow-Headers": "'Content-Type,X-Amz-Date,Authorization,X-Api-Key,X-Amz-Security-Token,X-Amz-User-Agent'",
                "method.response.header.Access-Control-Allow-Methods": "'OPTIONS,DELETE,GET,HEAD,PATCH,POST,PUT'",
                "method.response.header.Access-Control-Allow-Credentials": "'false'"
              },
              "ResponseTemplates": {
                "application/json": "#set($origin = $input.params(\"Origin\"))\n#if($origin == \"\") #set($origin = $input.params(\"origin\")) #end\n#if($origin.matches(\".*\")) #set($context.responseOverride.header.Access-Control-Allow-Origin = $origin) #end"
              }
            }
          ]
        },
        "ResourceId": {
          "Ref": "ApiGatewayResourceFoo"
        },
        "RestApiId": {
          "Ref": "ApiGatewayRestApi"
        }
      }
    },
    "ApiGatewayMethodProxyVarOptions": {
      "Type": "AWS::ApiGateway::Method",
      "Properties": {
        "AuthorizationType": "NONE",
        "HttpMethod": "OPTIONS",
        "MethodResponses": [
          {
            "StatusCode": "200",
            "ResponseParameters": {
              "method.response.header.Access-Control-Allow-Origin": true,
              "method.response.header.Access-Control-Allow-Headers": true,
              "method.response.header.Access-Control-Allow-Methods": true,
              "method.response.header.Access-Control-Allow-Credentials": true
            },
            "ResponseModels": {}
          }
        ],
        "RequestParameters": {},
        "Integration": {
          "Type": "MOCK",
          "RequestTemplates": {
            "application/json": "{statusCode:200}"
          },
          "ContentHandling": "CONVERT_TO_TEXT",
          "IntegrationResponses": [
            {
              "StatusCode": "200",
              "ResponseParameters": {
                "method.response.header.Access-Control-Allow-Origin": "'*'",
                "method.response.header.Access-Control-Allow-Headers": "'Content-Type,X-Amz-Date,Authorization,X-Api-Key,X-Amz-Security-Token,X-Amz-User-Agent'",
                "method.response.header.Access-Control-Allow-Methods": "'OPTIONS,DELETE,GET,HEAD,PATCH,POST,PUT'",
                "method.response.header.Access-Control-Allow-Credentials": "'false'"
              },
              "ResponseTemplates": {
                "application/json": "#set($origin = $input.params(\"Origin\"))\n#if($origin == \"\") #set($origin = $input.params(\"origin\")) #end\n#if($origin.matches(\".*\")) #set($context.responseOverride.header.Access-Control-Allow-Origin = $origin) #end"
              }
            }
          ]
        },
        "ResourceId": {
          "Ref": "ApiGatewayResourceProxyVar"
        },
        "RestApiId": {
          "Ref": "ApiGatewayRestApi"
        }
      }
    },
    "ApiGatewayMethodFooAny": {
      "Type": "AWS::ApiGateway::Method",
      "Properties": {
        "HttpMethod": "ANY",
        "RequestParameters": {},
        "ResourceId": {
          "Ref": "ApiGatewayResourceFoo"
        },
        "RestApiId": {
          "Ref": "ApiGatewayRestApi"
        },
        "ApiKeyRequired": false,
        "AuthorizationType": "NONE",
        "Integration": {
          "IntegrationHttpMethod": "POST",
          "Type": "AWS_PROXY",
          "Uri": {
            "Fn::Join": [
              "",
              [
                "arn:",
                {
                  "Ref": "AWS::Partition"
                },
                ":apigateway:",
                {
                  "Ref": "AWS::Region"
                },
                ":lambda:path/2015-03-31/functions/",
                {
                  "Fn::GetAtt": [
                    "AppLambdaFunction",
                    "Arn"
                  ]
                },
                "/invocations"
              ]
            ]
          }
        },
        "MethodResponses": []
      }
    },
    "ApiGatewayMethodProxyVarAny": {
      "Type": "AWS::ApiGateway::Method",
      "Properties": {
        "HttpMethod": "ANY",
        "RequestParameters": {},
        "ResourceId": {
          "Ref": "ApiGatewayResourceProxyVar"
        },
        "RestApiId": {
          "Ref": "ApiGatewayRestApi"
        },
        "ApiKeyRequired": false,
        "AuthorizationType": "NONE",
        "Integration": {
          "IntegrationHttpMethod": "POST",
          "Type": "AWS_PROXY",
          "Uri": {
            "Fn::Join": [
              "",
              [
                "arn:",
                {
                  "Ref": "AWS::Partition"
                },
                ":apigateway:",
                {
                  "Ref": "AWS::Region"
                },
                ":lambda:path/2015-03-31/functions/",
                {
                  "Fn::GetAtt": [
                    "AppLambdaFunction",
                    "Arn"
                  ]
                },
                "/invocations"
              ]
            ]
          }
        },
        "MethodResponses": []
      }
    },
    "ApiGatewayDeployment1568587328766": {
      "Type": "AWS::ApiGateway::Deployment",
      "Properties": {
        "RestApiId": {
          "Ref": "ApiGatewayRestApi"
        },
        "StageName": "production"
      },
      "DependsOn": [
        "ApiGatewayMethodFooOptions",
        "ApiGatewayMethodProxyVarOptions",
        "ApiGatewayMethodFooAny",
        "ApiGatewayMethodProxyVarAny"
      ]
    },
    "AppLambdaPermissionApiGateway": {
      "Type": "AWS::Lambda::Permission",
      "Properties": {
        "FunctionName": {
          "Fn::GetAtt": [
            "AppLambdaFunction",
            "Arn"
          ]
        },
        "Action": "lambda:InvokeFunction",
        "Principal": "apigateway.amazonaws.com",
        "SourceArn": {
          "Fn::Join": [
            "",
            [
              "arn:",
              {
                "Ref": "AWS::Partition"
              },
              ":execute-api:",
              {
                "Ref": "AWS::Region"
              },
              ":",
              {
                "Ref": "AWS::AccountId"
              },
              ":",
              {
                "Ref": "ApiGatewayRestApi"
              },
              "/*/*"
            ]
          ]
        }
      }
    }
  },
  "Outputs": {
    "ServerlessDeploymentBucketName": {
      "Value": {
        "Ref": "ServerlessDeploymentBucket"
      }
    },
    "AppLambdaFunctionQualifiedArn": {
      "Description": "Current Lambda function version",
      "Value": {
        "Ref": "AppLambdaVersion5re8i6ATiCM2Lv4joawdMQJI3Mvco3R6H5cLC3ZLT2I"
      }
    },
    "ServiceEndpoint": {
      "Description": "URL of the service endpoint",
      "Value": {
        "Fn::Join": [
          "",
          [
            "https://",
            {
              "Ref": "ApiGatewayRestApi"
            },
            ".execute-api.",
            {
              "Ref": "AWS::Region"
            },
            ".",
            {
              "Ref": "AWS::URLSuffix"
            },
            "/production"
          ]
        ]
      }
    }
  }
}